api/__init__.py
api/v0/api.py
api/v0/app/__init__.py
api/v0/app/api.py
api/v1/api.py
dashboards/dashboard_2/app.py
examples/example.py
examples/inverter_example.py
quartz_solar_forecast/__init__.py
quartz_solar_forecast/data.py
quartz_solar_forecast/evaluation.py
quartz_solar_forecast/forecast.py
quartz_solar_forecast/pydantic_models.py
quartz_solar_forecast/dataset/make_test_set.py
quartz_solar_forecast/eval/__init__.py
quartz_solar_forecast/eval/forecast.py
quartz_solar_forecast/eval/metrics.py
quartz_solar_forecast/eval/nwp.py
quartz_solar_forecast/eval/pv.py
quartz_solar_forecast/eval/utils.py
quartz_solar_forecast/forecasts/__init__.py
quartz_solar_forecast/forecasts/constants.py
quartz_solar_forecast/forecasts/v1.py
quartz_solar_forecast/forecasts/v1_tilt_orientation.py
quartz_solar_forecast/forecasts/v2.py
quartz_solar_forecast/inverters/__init__.py
quartz_solar_forecast/inverters/enphase.py
quartz_solar_forecast/inverters/givenergy.py
quartz_solar_forecast/inverters/inverter.py
quartz_solar_forecast/inverters/mock.py
quartz_solar_forecast/inverters/solarman.py
quartz_solar_forecast/inverters/solis.py
quartz_solar_forecast/inverters/victron.py
quartz_solar_forecast/models/model-0.4.0.pkl
quartz_solar_forecast/utils/__init__.py
quartz_solar_forecast/utils/file_path.py
quartz_solar_forecast/utils/forecast_csv.py
quartz_solar_forecast/utils/sentry_logging.py
quartz_solar_forecast/weather/__init__.py
quartz_solar_forecast/weather/open_meteo.py
quartz_solar_forecast-1.2.5.dist-info/licenses/LICENSE
scripts/download_tz-sam.py
scripts/forecast_csv.py
scripts/hf_upload.py
scripts/multi_site_generate_forecasts.py
scripts/run_evaluation.py
scripts/datapipes/__init__.py
scripts/datapipes/ocf_datapipe.py
tests/integration/eval/test_evaluation.py
tests/integration/eval/test_nwp.py
tests/integration/eval/test_pv.py
tests/unit/test_forecast.py
tests/unit/test_forecast_no_ts.py
tests/unit/test_generate_forecast.py
tests/unit/api_tests/v0/test_api.py
tests/unit/api_tests/v1/test_api_v1.py
tests/unit/data/test_make_test_set.py
quartz_solar_forecast-1.2.5.dist-info/METADATA
quartz_solar_forecast-1.2.5.dist-info/WHEEL
quartz_solar_forecast-1.2.5.dist-info/top_level.txt
quartz_solar_forecast-1.2.5.dist-info/RECORD
